setup.py
asgard/__init__.py
asgard/application.py
asgard/expression.py
asgard/sessions.py
asgard/tables.py
asgard/web.py
asgard.egg-info/PKG-INFO
asgard.egg-info/SOURCES.txt
asgard.egg-info/dependency_links.txt
asgard.egg-info/requires.txt
asgard.egg-info/top_level.txt
asgard/mails/__init__.py
asgard/users/__init__.py