Metadata-Version: 1.0
Name: asgard
Version: 0.5.0
Summary: asgard
Home-page: http://nowhere.com
Author: Nicolas Vanhoren
Author-email: nicolas.vanhoren@unknown.com
License: MIT
Platform: UNKNOWN
